harvest/__init__.py
harvest/algo.py
harvest/cli.py
harvest/definitions.py
harvest/server.py
harvest/utils.py
harvest/wizard.py
harvest/api/__init__.py
harvest/api/_base.py
harvest/api/alpaca.py
harvest/api/dummy.py
harvest/api/kraken.py
harvest/api/paper.py
harvest/api/polygon.py
harvest/api/robinhood.py
harvest/api/webull.py
harvest/api/yahoo.py
harvest/gui/global.css
harvest/gui/index.html
harvest/gui/build/bundle.css
harvest/gui/build/bundle.js
harvest/gui/build/bundle.js.map
harvest/gui/minimal/login.html
harvest/gui/minimal/update_password.html
harvest/plugin/__init__.py
harvest/plugin/_base.py
harvest/plugin/dolt_options_plugin.py
harvest/storage/__init__.py
harvest/storage/base_storage.py
harvest/storage/csv_storage.py
harvest/storage/database_storage.py
harvest/storage/pickle_storage.py
harvest/trader/__init__.py
harvest/trader/tester.py
harvest/trader/trader.py
harvest/util/__init__.py
harvest/util/factory.py
harvest_python-0.4.0.dist-info/LICENSE
harvest_python-0.4.0.dist-info/METADATA
harvest_python-0.4.0.dist-info/WHEEL
harvest_python-0.4.0.dist-info/entry_points.txt
harvest_python-0.4.0.dist-info/top_level.txt
harvest_python-0.4.0.dist-info/RECORD
