Metadata-Version: 2.1
Name: harvest-python
Version: 0.4.0
Summary: Simple and intuitive python framework for algorithmic trading.
Home-page: https://github.com/tfukaza/harvest/
Author: Harvest Team
License: UNKNOWN
Platform: UNKNOWN
Classifier: Programming Language :: Python :: 3
Classifier: License :: OSI Approved :: MIT License
Classifier: Operating System :: OS Independent
Requires-Python: >=3.9
License-File: LICENSE
Requires-Dist: pandas (==1.3.5)
Requires-Dist: finta (>=1.3)
Requires-Dist: pyyaml
Requires-Dist: tqdm
Requires-Dist: tzlocal (>=3.0)
Requires-Dist: tzdata
Requires-Dist: yfinance
Requires-Dist: SQLAlchemy
Requires-Dist: flask-login
Requires-Dist: flask-cors
Requires-Dist: flask
Requires-Dist: rich
Provides-Extra: alpaca
Requires-Dist: alpaca-trade-api ; extra == 'alpaca'
Provides-Extra: dev
Requires-Dist: coverage ; extra == 'dev'
Requires-Dist: black ; extra == 'dev'
Provides-Extra: kraken
Requires-Dist: krakenex ; extra == 'kraken'
Provides-Extra: robinhood
Requires-Dist: pyotp ; extra == 'robinhood'
Requires-Dist: robin-stocks ; extra == 'robinhood'
Provides-Extra: webull
Requires-Dist: webull ; extra == 'webull'
